{
  "schema_version": "1.0.0",
  "created_at": "2026-04-18T19:05:28Z",
  "phase": "phase3",
  "task": "chain_sparse_long",
  "algorithm": "SafePE",
  "seed": 11,
  "final_bellman_residual": 0.9988906256575312,
  "n_sweeps": 1,
  "wall_clock_s": 0.0020632910018321127,
  "converged": true,
  "n_states": 60,
  "schedule_sign": 1,
  "beta_used_min": 2.8479469269452537e-06,
  "beta_used_max": 0.0020100912797734152,
  "n_stages_clipped": 120,
  "clip_fraction": 1.0,
  "sweeps_to_1e-2": null,
  "sweeps_to_1e-4": null,
  "sweeps_to_1e-6": null
}
